PyIPe.py
PyIPe-1.1.dist-info/METADATA
PyIPe-1.1.dist-info/WHEEL
PyIPe-1.1.dist-info/top_level.txt
PyIPe-1.1.dist-info/RECORD
