Metadata-Version: 2.1
Name: PyIPe
Version: 1.1
Summary: library to get everything about location and anti vpn
Author: twinsszi
Author-email: adhm90879@email.com
Keywords: ip,location,country,latitude,longitude,vpn
Classifier: Programming Language :: Python :: 3
Classifier: License :: OSI Approved :: MIT License
Classifier: Operating System :: OS Independent
Requires-Python: >=3.6
Requires-Dist: requests
